CHANGES
CONTRIB
LICENSE
MANIFEST.in
README
jose.py
requirements.txt
setup.py
jose.egg-info/PKG-INFO
jose.egg-info/SOURCES.txt
jose.egg-info/dependency_links.txt
jose.egg-info/entry_points.txt
jose.egg-info/requires.txt
jose.egg-info/top_level.txt