Metadata-Version: 1.1
Name: jose
Version: 0.2.2
Summary: An implementation of the JOSE draft
Home-page: https://github.com/Demonware/jose
Author: Demian Brecht
Author-email: dbrecht@demonware.net
License: UNKNOWN
Platform: UNKNOWN
Classifier: Development Status :: 4 - Beta
Classifier: Intended Audience :: Developers
Classifier: Intended Audience :: Information Technology
Classifier: License :: OSI Approved :: BSD License
Classifier: Operating System :: OS Independent
Classifier: Programming Language :: Python :: 2 :: Only
Classifier: Topic :: Security
Classifier: Topic :: Software Development :: Libraries
